{
	"type": "home",
	"blocks": [
		{
			"type": "header",
			"text": {
				"type": "plain_text",
				"text": ":wave: Hi! I'm Atom"
			}
		},
		{
			"type": "section",
			"text": {
				"type": "mrkdwn",
				"text": ":sparkles: Atomicwork asked me to assist you and answer your questions."
			}
		},
		{
			"type": "section",
			"text": {
				"type": "mrkdwn",
				"text": "💬 Ask me any questions you might have like how to set up a VPN or add a dependant to your health insurance."
			}
		},
		{
			"type": "section",
			"text": {
				"type": "mrkdwn",
				"text": ":ballot_box_with_ballot: I can also help you raise requests for things like a new monitor, software access and more!"
			}
		},
		{
			"type": "section",
			"text": {
				"type": "plain_text",
				"text": "  ",
				"emoji": true
			}
		},
		{
			"type": "section",
			"text": {
				"type": "plain_text",
				"text": "  ",
				"emoji": true
			}
		},
		{
			"type": "header",
			"text": {
				"type": "plain_text",
				"text": "Requested by you"
			}
		},
		{
			"type": "divider"
		},
		{
			"type": "actions",
			"elements": [
				{
					"type": "button",
					"text": {
						"type": "plain_text",
						"text": "Open and pending",
						"emoji": true
					},
					"value": "click_me_123",
					"action_id": "actionId-0"
				},
				{
					"type": "button",
					"text": {
						"type": "plain_text",
						"text": "Completed",
						"emoji": true
					},
					"value": "click_me_123",
					"action_id": "actionId-1"
				}
			]
		},
		{
			"type": "section",
			"text": {
				"type": "mrkdwn",
				"text": "*Open and pending (6)*"
			}
		},
		{
			"type": "section",
			"text": {
				"type": "mrkdwn",
				"text": "*<fakelink.toUrl.com|REQ-102: I need access to salesforce>* \n _Recent message:_ You request is being processed"
			}
		},
		{
			"type": "context",
			"elements": [
				{
					"type": "mrkdwn",
					"text": "*Status:* Pending"
				},
				{
					"type": "mrkdwn",
					"text": "*Agent:* <fakelink.toUrl.com|@John appleseed>"
				}
			]
		},
		{
			"type": "section",
			"text": {
				"type": "mrkdwn",
				"text": "*<fakelink.toUrl.com|INC-12: Our customer access portal for payments is not working>* \n _Description:_ Our access to the payment gateway seems to be throwing an error \n"
			}
		},
		{
			"type": "context",
			"elements": [
				{
					"type": "mrkdwn",
					"text": "*Status:* Pending"
				},
				{
					"type": "mrkdwn",
					"text": "*Agent:* <fakelink.toUrl.com|@William alright>"
				}
			]
		},
		{
			"type": "section",
			"text": {
				"type": "mrkdwn",
				"text": "*<fakelink.toUrl.com|SR-12: Planning a business travel for the yearly offsite>* \n _Recent message:_ This is the most recent message on the request \n"
			}
		},
		{
			"type": "context",
			"elements": [
				{
					"type": "mrkdwn",
					"text": "*Status:* Pending"
				},
				{
					"type": "mrkdwn",
					"text": "*Agent:* Unassigned"
				}
			]
		},
		{
			"type": "actions",
			"elements": [
				{
					"type": "button",
					"text": {
						"type": "plain_text",
						"text": "View 3 more",
						"emoji": true
					},
					"value": "click_me_123",
					"action_id": "actionId-0"
				}
			]
		},
		{
			"type": "divider"
		}
	]
}
